MANIFEST.in
agtl
setup.py
advancedcaching/__init__.py
advancedcaching/abstractmap.py
advancedcaching/astral.py
advancedcaching/biggui.py
advancedcaching/cachedownloader.py
advancedcaching/cli.py
advancedcaching/colorer.py
advancedcaching/connection.py
advancedcaching/coordfinder.py
advancedcaching/core.py
advancedcaching/downloader.py
advancedcaching/exporter.py
advancedcaching/extListview.py
advancedcaching/fieldnotesuploader.py
advancedcaching/geo.py
advancedcaching/geocaching.py
advancedcaching/geonames.py
advancedcaching/gpsreader.py
advancedcaching/gtkmap.py
advancedcaching/gui.py
advancedcaching/hildon_plugins.py
advancedcaching/hildongui.py
advancedcaching/openstreetmap.py
advancedcaching/portrait.py
advancedcaching/provider.py
advancedcaching/pyfo.py
advancedcaching/qtgui.py
advancedcaching/run-core.py
advancedcaching/setup.py
advancedcaching/simplegui.py
advancedcaching/threadpool.py
advancedcaching/data/accept.png
advancedcaching/data/asterisk_yellow.png
advancedcaching/data/calendar_edit.png
advancedcaching/data/comment.png
advancedcaching/data/cross.png
advancedcaching/data/delete.png
advancedcaching/data/desktop.glade
advancedcaching/data/emoticon_grin.png
advancedcaching/data/error.png
advancedcaching/data/freerunner.glade
advancedcaching/data/group.png
advancedcaching/data/main.glade
advancedcaching/data/noimage-cantload.png
advancedcaching/data/noimage-loading.png
advancedcaching/data/noimage.png
advancedcaching/data/options.glade
advancedcaching/data/simple.glade
advancedcaching/data/wrench.png
agtl.egg-info/PKG-INFO
agtl.egg-info/SOURCES.txt
agtl.egg-info/dependency_links.txt
agtl.egg-info/top_level.txt