Metadata-Version: 1.0
Name: agtl
Version: 0.8.0.7
Summary: Towards paperless geocaching
Home-page: http://wiki.openmoko.org/wiki/Advanced_Geocaching_Tool_for_Linux
Author: Daniel Fett
Author-email: agtl@fragcom.de
License: UNKNOWN
Platform: UNKNOWN
Classifier: Development Status :: 4 - Beta
Classifier: Environment :: X11 Applications
Classifier: Intended Audience :: End Users/Desktop
Classifier: License :: OSI Approved :: GNU General Public License (GPL)
Classifier: Programming Language :: Python
